pyqmc/__init__.py
pyqmc/api.py
pyqmc/gpu.py
pyqmc/pyscftools.py
pyqmc/reblock.py
pyqmc/recipes.py
pyqmc/wftools.py
pyqmc/configurations/coord.py
pyqmc/configurations/distance.py
pyqmc/method/dmc.py
pyqmc/method/ensemble_optimization.py
pyqmc/method/ensemble_optimization_wfbywf.py
pyqmc/method/hdftools.py
pyqmc/method/linemin.py
pyqmc/method/mc.py
pyqmc/method/optimize_excited_states.py
pyqmc/method/optimize_ortho.py
pyqmc/method/optvariance.py
pyqmc/method/sample_many.py
pyqmc/observables/accumulators.py
pyqmc/observables/accumulators_multiwf.py
pyqmc/observables/ecp_accumulator.py
pyqmc/observables/energy.py
pyqmc/observables/eval_ecp.py
pyqmc/observables/ewald.py
pyqmc/observables/ewald2d.py
pyqmc/observables/jax_ecp.py
pyqmc/observables/obdm.py
pyqmc/observables/stochastic_reconfiguration.py
pyqmc/observables/tbdm.py
pyqmc/pbc/pbc.py
pyqmc/pbc/supercell.py
pyqmc/pbc/twists.py
pyqmc/wf/addwf.py
pyqmc/wf/determinant_tools.py
pyqmc/wf/func3d.py
pyqmc/wf/geminaljastrow.py
pyqmc/wf/gps2.py
pyqmc/wf/jastrowspin.py
pyqmc/wf/multiplywf.py
pyqmc/wf/orbitals.py
pyqmc/wf/slater.py
pyqmc/wf/testwf.py
pyqmc/wf/three_body_jastrow.py
pyqmc/wf/jax/__init__.py
pyqmc/wf/jax/gto.py
pyqmc/wf/jax/jastrowspin.py
pyqmc/wf/jax/slater.py
pyqmc/wf/numba/gto.py
pyqmc/wf/numba/pbcgto.py
pyqmc/wf/numba/spherical_harmonics.py
pyqmc-0.8.0.dist-info/licenses/LICENSE
pyqmc-0.8.0.dist-info/WHEEL
pyqmc-0.8.0.dist-info/METADATA
pyqmc-0.8.0.dist-info/RECORD
