Metadata-Version: 2.4
Name: pyqmc
Version: 0.8.0
Summary: Real-space quantum Monte Carlo (QMC) methods for electronic structure calculations.
Author-email: Lucas Wagner <lkwagner@illinois.edu>
Requires-Python: >=3.10
License-File: LICENSE
Requires-Dist: scipy (>=1.10.0,<2.0.0)
Requires-Dist: pyscf (>=2.8.0,<3.0.0)
Requires-Dist: h5py (>=3.13.0,<4.0.0)
Requires-Dist: pandas (>=2.2.3,<3.0.0)
